ShiyanlouJavaJiaochengHeji20160904Fix1/README.md
ShiyanlouJavaJiaochengHeji20160904Fix1/__init__.py
ShiyanlouJavaJiaochengHeji20160904Fix1/__main__.py
ShiyanlouJavaJiaochengHeji20160904Fix1/file.epub
ShiyanlouJavaJiaochengHeji20160904Fix1/index.html
ShiyanlouJavaJiaochengHeji20160904Fix1/css/__init__.py
ShiyanlouJavaJiaochengHeji20160904Fix1/css/annotations.css
ShiyanlouJavaJiaochengHeji20160904Fix1/css/main.css
ShiyanlouJavaJiaochengHeji20160904Fix1/css/normalize.css
ShiyanlouJavaJiaochengHeji20160904Fix1/css/popup.css
ShiyanlouJavaJiaochengHeji20160904Fix1/font/__init__.py
ShiyanlouJavaJiaochengHeji20160904Fix1/font/fontello.eot
ShiyanlouJavaJiaochengHeji20160904Fix1/font/fontello.svg
ShiyanlouJavaJiaochengHeji20160904Fix1/font/fontello.ttf
ShiyanlouJavaJiaochengHeji20160904Fix1/font/fontello.woff
ShiyanlouJavaJiaochengHeji20160904Fix1/img/__init__.py
ShiyanlouJavaJiaochengHeji20160904Fix1/img/annotator-glyph-sprite.png
ShiyanlouJavaJiaochengHeji20160904Fix1/img/annotator-icon-sprite.png
ShiyanlouJavaJiaochengHeji20160904Fix1/img/apple-touch-icon.png
ShiyanlouJavaJiaochengHeji20160904Fix1/img/cancelfullscreen.png
ShiyanlouJavaJiaochengHeji20160904Fix1/img/close.png
ShiyanlouJavaJiaochengHeji20160904Fix1/img/fullscreen.png
ShiyanlouJavaJiaochengHeji20160904Fix1/img/loader.gif
ShiyanlouJavaJiaochengHeji20160904Fix1/img/menu-icon.png
ShiyanlouJavaJiaochengHeji20160904Fix1/img/save.png
ShiyanlouJavaJiaochengHeji20160904Fix1/img/saved.png
ShiyanlouJavaJiaochengHeji20160904Fix1/img/settings-s.png
ShiyanlouJavaJiaochengHeji20160904Fix1/img/settings.png
ShiyanlouJavaJiaochengHeji20160904Fix1/img/star.png
ShiyanlouJavaJiaochengHeji20160904Fix1/js/__init__.py
ShiyanlouJavaJiaochengHeji20160904Fix1/js/epub.js
ShiyanlouJavaJiaochengHeji20160904Fix1/js/epub.min.js
ShiyanlouJavaJiaochengHeji20160904Fix1/js/epub.min.map
ShiyanlouJavaJiaochengHeji20160904Fix1/js/hooks.min.js
ShiyanlouJavaJiaochengHeji20160904Fix1/js/hooks.min.map
shiyanlou_java_jiaocheng_heji_20160904_fix1-2024.3.2.0.dist-info/METADATA
shiyanlou_java_jiaocheng_heji_20160904_fix1-2024.3.2.0.dist-info/WHEEL
shiyanlou_java_jiaocheng_heji_20160904_fix1-2024.3.2.0.dist-info/entry_points.txt
shiyanlou_java_jiaocheng_heji_20160904_fix1-2024.3.2.0.dist-info/top_level.txt
shiyanlou_java_jiaocheng_heji_20160904_fix1-2024.3.2.0.dist-info/RECORD
